libarl/__init__.py
libarl/core.cpython-310-x86_64-linux-gnu.so
libarl-0.0.1.3625797450.dist-info/entry_points.txt
libarl-0.0.1.3625797450.dist-info/METADATA
libarl-0.0.1.3625797450.dist-info/top_level.txt
libarl-0.0.1.3625797450.dist-info/RECORD
libarl-0.0.1.3625797450.dist-info/WHEEL
libarl-0.0.1.3625797450.dist-info/LICENSE
