Metadata-Version: 2.1
Name: libarl
Version: 0.0.1.3625797450
Summary: Core ARL model evaluator library
Home-page: https://github.com/fvutils/libarl
Author: Matthew Ballance
Author-email: matt.ballance@gmail.com
License: Apache 2.0
Keywords: SystemVerilog,Verilog,RTL,Python
License-File: LICENSE
Requires-Dist: libvsc
